darknet_config_generator/__init__.py
darknet_config_generator/common.py
darknet_config_generator/yolo_connections.py
darknet_config_generator/yolo_darknet.py
darknet_config_generator/yolo_layers.py
darknet_config_generator/yolo_network.py
darknet_config_generator/yolo_optimizers.py
darknet_config_generator/yolo_preprocess.py
darknet_config_generator-1.0.1.dist-info/LICENSE
darknet_config_generator-1.0.1.dist-info/METADATA
darknet_config_generator-1.0.1.dist-info/WHEEL
darknet_config_generator-1.0.1.dist-info/top_level.txt
darknet_config_generator-1.0.1.dist-info/RECORD
