Metadata-Version: 2.1
Name: darknet-config-generator
Version: 1.0.1
Summary: Darknet Neural Network Configuration Generator
Home-page: https://adamuas.github.io/darknet-neural-net-config-generator/
Author: Abdullahi S. Adamu
Author-email: abdullah.adam89@gmail.com
License: UNKNOWN
Platform: UNKNOWN
Classifier: Programming Language :: Python :: 3
Classifier: License :: OSI Approved :: MIT License
Classifier: Operating System :: OS Independent
Requires-Python: >=3.6
